gpx/__init__.py
gpx/_version.py
gpx/old/__init__.py
gpx/old/cov.py
gpx/old/gp.py
gpx/old/hsgp_approx.py
gpx/old/mean.py
gpx/old/util.py
pymc_gpx-0.0.1.dist-info/METADATA
pymc_gpx-0.0.1.dist-info/WHEEL
pymc_gpx-0.0.1.dist-info/licenses/LICENSE.txt
pymc_gpx-0.0.1.dist-info/RECORD
