Metadata-Version: 2.3
Name: pymc-gpx
Version: 0.0.1
Summary: Unstable and experimental new Gaussian Process implementation for PyMC
Project-URL: Documentation, https://github.com/maresb/pymc-gpx#readme
Project-URL: Issues, https://github.com/maresb/pymc-gpx/issues
Project-URL: Source, https://github.com/maresb/pymc-gpx
Author-email: Ben Mares <services-git-throwaway1@tensorial.com>
License-Expression: Apache-2.0
License-File: LICENSE.txt
Classifier: Development Status :: 4 - Beta
Classifier: Intended Audience :: Science/Research
Classifier: License :: OSI Approved :: Apache Software License
Classifier: Operating System :: OS Independent
Classifier: Programming Language :: Python
Classifier: Programming Language :: Python :: 3
Classifier: Programming Language :: Python :: 3.10
Classifier: Programming Language :: Python :: 3.11
Classifier: Programming Language :: Python :: 3.12
Classifier: Topic :: Scientific/Engineering
Classifier: Topic :: Scientific/Engineering :: Mathematics
Requires-Python: >=3.10
Requires-Dist: pymc>=5
